{
  "description": "Reverse-and-diminish demag principle, split layout. LEFT: applied magnetizing force vs time — alternating waveform decaying to zero inside a dashed amber envelope, START ≥ ORIGINAL FIELD marker on the first peak. RIGHT: B–H plane with hysteresis loops re-tracing smaller and smaller, collapsing to a dot at the origin.",
  "reveals": [
    { "kind": "draw", "id": "ddaAxes", "at": 0.8 },
    { "kind": "fade", "id": "ddaAxesLbl", "at": 1.5 },
    { "kind": "draw", "id": "ddaWave", "at": 2.0 },
    { "kind": "fade", "id": "ddaEnvelope", "at": 4.2 },
    { "kind": "fade", "id": "ddaStart", "at": 5.6 }, { "kind": "ping", "id": "ddaStartPing", "at": 5.6 },
    { "kind": "draw", "id": "ddaLoops", "at": 7.2 },
    { "kind": "fade", "id": "ddaLoopsDot", "at": 7.5 }
  ]
}
