{
  "description": "Intensifying factor as a picture: IF = exposure without screens over exposure with screens, tall BARE bar vs short WITH-SCREENS bar feeding an IF ratio chip; right, LEAD FOIL card with crisp mini-radiograph (IF 2-4) vs FLUORESCENT phosphor card (IF 10-100) whose radiograph blooms soft with sideways light rays and mottle grain at 8s while the lead image stays crisp.",
  "reveals": [
    { "kind": "fade", "id": "ifxFormula", "at": 0.5 },
    { "kind": "draw", "id": "ifxBars", "at": 1.1 },
    { "kind": "fade", "id": "ifxRatio", "at": 2.4 },
    { "kind": "fade", "id": "ifxLead", "at": 4.0 },
    { "kind": "fade", "id": "ifxFluoro", "at": 6.0 },
    { "kind": "fade", "id": "ifxBlur", "at": 8.0 }
  ]
}
