{
  "lessonId": "basic-1-4",
  "displayTitle": "The Certificate Proves; the Employer Authorizes",
  "anchorAfterSection": 1,
  "kicker": "BASIC // ASNT NDT LEVEL III PROGRAM",
  "beats": [
    {
      "type": "title",
      "narration": "Every other credential lives inside the employer's walls. The ASNT Level Three certificate is the rare one that travels with you between jobs.",
      "payload": {
        "title": "EVIDENCE IS CENTRAL",
        "sub": "An outside body examines you; the certificate is yours to carry.",
        "panel": "records-vault",
        "panelLabel": "THIRD-PARTY CERTIFICATE // PORTABLE PROOF"
      }
    },
    {
      "type": "tiles",
      "narration": "Eligibility trades schooling against field time, but experience never hits zero. More technical education, less required NDT experience comparable to Level Two.",
      "payload": {
        "heading": "Education trades against experience",
        "tiles": [
          { "icon": "certificate", "t": "4-yr degree", "s": "1 year of NDT experience" },
          { "icon": "book-2", "t": "2-yr study", "s": "2 years of experience" },
          { "icon": "user-check", "t": "High school", "s": "4 years of experience" }
        ]
      }
    },
    {
      "type": "list",
      "narration": "Then two exams. The Basic, taken once, covers this common core; a Method exam, one per endorsement, goes deep at Level Three depth.",
      "payload": {
        "heading": "Two exams, one certificate",
        "chips": [
          { "icon": "list-check", "t": "Basic exam", "s": "Once — the core you study now" },
          { "icon": "microscope", "t": "Method exam", "s": "One per method endorsement" },
          { "icon": "percentage", "t": "Pass or fail", "s": "Proctored, around 70 percent" },
          { "icon": "history", "t": "Valid 5 years", "s": "Reexam or earned credits" }
        ]
      }
    },
    {
      "type": "diagram",
      "narration": "Here is the point exams love. Passing proves knowledge. It does not let you sign anything until an employer certifies you under its own written practice.",
      "payload": {
        "heading": "Proof travels; authority is granted",
        "asset": "central-vs-local-cert",
        "note": "ASNT CERTIFICATE = QUALIFICATION EVIDENCE · EMPLOYER DESIGNATION = AUTHORITY TO ACT",
        "noteAt": 8.5
      }
    },
    {
      "type": "kinetic",
      "narration": "Hold the line in your head. The certificate is qualification evidence. The employer's act is authority. The exam tests whether you keep them apart.",
      "payload": {
        "lines": [
          { "t": "EVIDENCE IS CENTRAL." },
          { "t": "AUTHORITY IS LOCAL." },
          { "t": "KEEP THEM APART." }
        ],
        "sub": "Five endorsements still can't sign a procedure until a company makes you its Level III."
      }
    }
  ]
}
