{
  "lessonId": "et2-8-5",
  "displayTitle": "When Permeability Becomes the Signal",
  "anchorAfterSection": 1,
  "kicker": "ET LEVEL II // FERROMAGNETIC PROPERTY MEASUREMENT",
  "beats": [
    {
      "type": "title",
      "narration": "Through the flaw-detection arc, permeability was noise you saturated away on steel. Property measurement flips it — permeability becomes the signal.",
      "payload": {
        "title": "PERMEABILITY IS THE SIGNAL",
        "sub": "The villain of flaw work becomes the measurement.",
        "panel": "pipe-scan",
        "panelLabel": "ET COIL // PROPERTY SORT"
      }
    },
    {
      "type": "tiles",
      "narration": "The same microstructure that sets hardness pins magnetic domain walls. So heat treat, carbon, and cold work all rewrite the magnetic properties together.",
      "payload": {
        "heading": "Microstructure writes both",
        "tiles": [
          { "icon": "atom-2", "t": "Domain walls", "s": "Obstacles pin them" },
          { "icon": "bolt", "t": "Hardness", "s": "Same obstacles block slip" },
          { "icon": "flame", "t": "Heat treat", "s": "Carbon, case, cold work" }
        ]
      }
    },
    {
      "type": "diagram",
      "narration": "Read it on the hysteresis loop. A hardened part draws a wide, flat loop; an annealed part a tall, narrow one.",
      "payload": {
        "heading": "The loop carries the story",
        "asset": "hysteresis-loops",
        "note": "HARD = WIDE LOOP · ANNEALED = NARROW LOOP",
        "noteAt": 9.0
      }
    },
    {
      "type": "list",
      "narration": "The instrument is a comparator bridge — matched coils, a verified reference in one, the test part in the other. Matched parts null; any difference unbalances it.",
      "payload": {
        "heading": "Null means match",
        "chips": [
          { "icon": "layers-intersect", "t": "Two coils", "s": "Reference vs test part" },
          { "icon": "target", "t": "Null = match", "s": "Same permeability, balanced" },
          { "icon": "activity", "t": "Difference reads", "s": "Unbalance amplitude and phase" }
        ]
      }
    },
    {
      "type": "kinetic",
      "narration": "So demagnetize, equalize temperature, run low frequency, build the window from verified parts. The bridge reports difference — the laboratory proves the cause.",
      "payload": {
        "lines": [
          { "t": "DEMAG · EQUALIZE" },
          { "t": "BUILD THE WINDOW" },
          { "t": "VERIFY THE CAUSE" }
        ],
        "sub": "The meter never gets the final word on a borderline part."
      }
    }
  ]
}
