{
  "lessonId": "et2-1-2",
  "displayTitle": "Choosing the Probe, and Defending It",
  "anchorAfterSection": 1,
  "kicker": "ET LEVEL II // PROBE SELECTION",
  "beats": [
    {
      "type": "title",
      "narration": "At Level Two you don't just run the probe — you pick it and defend the pick. A flaw the probe can't see never becomes data.",
      "payload": {
        "title": "CHOOSE THE PROBE",
        "sub": "A flaw the probe can't see never becomes data.",
        "panel": "pipe-scan",
        "panelLabel": "ET PROBE // TUBE SCAN"
      }
    },
    {
      "type": "tiles",
      "narration": "Every probe is three stacked decisions: where the coil sits, how it's wound and connected, and what physically senses the field.",
      "payload": {
        "heading": "Every probe is three decisions",
        "tiles": [
          { "icon": "target", "t": "Configure", "s": "Surface, encircling, bobbin" },
          { "icon": "wave-sine", "t": "Wind & mode", "s": "Absolute or differential" },
          { "icon": "bolt", "t": "Sense", "s": "Coil or Hall element" }
        ]
      }
    },
    {
      "type": "diagram",
      "narration": "Mode decides what reaches the screen. Absolute sees everything, including drift. Differential cancels what's shared, drawing two lobes on local flaws. Reflection splits driver from pickup.",
      "payload": {
        "heading": "Three modes, three signatures",
        "asset": "et-operating-modes",
        "note": "ABSOLUTE SEES ALL · DIFFERENTIAL CANCELS SHARED · REFLECTION SPLITS",
        "noteAt": 9.0
      }
    },
    {
      "type": "list",
      "narration": "And orientation can beat you. A bobbin's currents run circumferential, so circumferential cracks hide. The fix isn't a setting — it's a different coil.",
      "payload": {
        "heading": "Orientation problems need a new coil",
        "chips": [
          { "icon": "x", "t": "Bobbin, circ crack", "s": "Currents lie parallel — missed" },
          { "icon": "check", "t": "Rotating pancake", "s": "Small loops cut any crack" },
          { "icon": "refresh", "t": "Array probe", "s": "Same coverage, far faster" }
        ]
      }
    },
    {
      "type": "kinetic",
      "narration": "Coils carry conventional work; as frequency falls toward DC, Hall sensors take over. Close every choice with configuration, mode, element — or you chose by habit.",
      "payload": {
        "lines": [
          { "t": "CONFIGURATION." },
          { "t": "MODE." },
          { "t": "ELEMENT." }
        ],
        "sub": "Say all three, or the flaw didn't pick the probe."
      }
    }
  ]
}
