{
  "lessonId": "pt2-5-4",
  "displayTitle": "One Weld, Start to Signed Record",
  "anchorAfterSection": 1,
  "kicker": "PT LEVEL II // CAPSTONE",
  "beats": [
    {
      "type": "title",
      "narration": "One nozzle weld, the whole Level Two job. The code picks the method, the appendix picks the criteria, your procedure ties them together.",
      "payload": {
        "title": "ONE WELD, START TO FINISH",
        "sub": "Verify, interpret, classify, disposition, document — in order.",
        "panel": "flowdown",
        "panelLabel": "SECTION VIII // APPENDIX 8 // PT-204"
      }
    },
    {
      "type": "tiles",
      "narration": "Before you read one indication, prove the test was valid. Right procedure revision, qualified materials logged, parameters in window, white light measured.",
      "payload": {
        "heading": "Step zero: earn the right to interpret",
        "tiles": [
          { "icon": "clipboard-check", "t": "Revision", "s": "PT-204 Rev C on bench" },
          { "icon": "droplet", "t": "Materials", "s": "In date, batches logged" },
          { "icon": "gauge", "t": "Process", "s": "Temp, dwell in window" },
          { "icon": "bulb", "t": "Light", "s": "100 fc, measured" }
        ]
      }
    },
    {
      "type": "tiles",
      "narration": "Now interpret every indication before measuring anything. A smear that wipes and stays gone is false. A line tracing the faying edge is geometry.",
      "payload": {
        "heading": "Sort first: three buckets",
        "tiles": [
          { "icon": "x", "t": "False", "s": "Wipes off, never returns" },
          { "icon": "history", "t": "Nonrelevant", "s": "Geometry, noted not graded" },
          { "icon": "alert-triangle", "t": "Relevant", "s": "Returns — gets measured" }
        ]
      }
    },
    {
      "type": "diagram",
      "narration": "Measure the indication, not the flaw, at development time. A toe line a quarter inch by a sixteenth is four-to-one linear. The pattern permits none.",
      "payload": {
        "heading": "Classify, then disposition",
        "asset": "indication-ladder",
        "note": "4:1 LINEAR > 3:1 — RELEVANT, NONE PERMITTED, REJECT",
        "noteAt": 9.5
      }
    },
    {
      "type": "kinetic",
      "narration": "Reject, route the defect, reprocess from step zero. Then the record stands alone — cited, traceable, corrected with a single line, never erased.",
      "payload": {
        "lines": [
          { "t": "CITE THE CODE." },
          { "t": "ONE ROW EACH." },
          { "t": "STANDS ALONE." }
        ],
        "sub": "A stranger with only your record reaches your call."
      }
    }
  ]
}
